{
  "reflection": [
    {
      "type": "org.thymeleaf.expression.Temporals",
      "methods": [
        {
          "name": "format",
          "parameterTypes": [
            "java.time.temporal.Temporal",
            "java.lang.String"
          ]
        },
        {
          "name": "formatISO",
          "parameterTypes": [
            "java.time.temporal.Temporal"
          ]
        }
      ]
    },
    {
      "type": "org.thymeleaf.expression.Dates",
      "methods": [
        {
          "name": "format",
          "parameterTypes": [
            "java.util.Calendar",
            "java.lang.String"
          ]
        }
      ]
    }
  ],
  "serialization": [
    {
      "type": "java.time.Instant"
    }
  ]
}
